LICENSE
MANIFEST.in
README.rst
overload.py
setup.py
p2_overload.egg-info/PKG-INFO
p2_overload.egg-info/SOURCES.txt
p2_overload.egg-info/dependency_links.txt
p2_overload.egg-info/top_level.txt